pdfzip/__init__.py
pdfzip/compressor.py
tests/__init__.py
tests/test_compressor.py
pdfzip-0.1.0.dist-info/LICENSE
pdfzip-0.1.0.dist-info/METADATA
pdfzip-0.1.0.dist-info/WHEEL
pdfzip-0.1.0.dist-info/entry_points.txt
pdfzip-0.1.0.dist-info/top_level.txt
pdfzip-0.1.0.dist-info/RECORD
