Metadata-Version: 2.1
Name: pdfzip
Version: 0.1.0
Summary: A simple PDF compressor using Ghostscript
Home-page: https://github.com/dev-r4hul/pdfzip
Author: Rahul Choudhary
Author-email: goodluckrahul@yahoo.com
License: UNKNOWN
Platform: UNKNOWN
Classifier: Programming Language :: Python :: 3
Classifier: License :: OSI Approved :: MIT License
Classifier: Operating System :: OS Independent
Requires-Python: >=3.6
License-File: LICENSE
